usoptimize/__init__.py
usoptimize/cli.py
usoptimize/convert.py
usoptimize/qtfaststart2/__init__.py
usoptimize/qtfaststart2/exceptions.py
usoptimize/qtfaststart2/processor.py
usoptimize-0.2.dist-info/LICENSE
usoptimize-0.2.dist-info/METADATA
usoptimize-0.2.dist-info/WHEEL
usoptimize-0.2.dist-info/entry_points.txt
usoptimize-0.2.dist-info/top_level.txt
usoptimize-0.2.dist-info/RECORD
