Metadata-Version: 2.1
Name: usoptimize
Version: 0.2
Summary: A Python CLI UltraStar Song Converter to optimize song files for the web.
Home-page: https://github.com/ZerNico/ultrastar-stream-optimizer
Author-email: nico.franke01@gmail.com
License: MIT
Platform: UNKNOWN
Classifier: License :: OSI Approved :: MIT License
Classifier: Programming Language :: Python :: 3
Classifier: Programming Language :: Python :: 3.7
License-File: LICENSE
Requires-Dist: tqdm (==4.64.0)
Requires-Dist: chardet (==3.0.4)
Requires-Dist: ffmpeg-python (==0.2.0)
